{"word": "Pettegola", "municipalities": {"Adrara San Martino": "pet\u00f2nega", "Adrara San Rocco": "pet\u00f2nega", "Albano Sant'Alessandro": "pet\u00f2nega", "Albino": "pet\u00f2nega", "Algua": "pet\u00f2nega", "Alme": "pet\u00f2nega", "Almenno San Bartolomeo": "pet\u00f2nega", "Almenno San Salvatore": "pet\u00f2nega", "Alzano Lombardo": "pet\u00f2nega", "Ambivere": "pet\u00f2nega", "Antegnate": "pet\u00f2nega", "Arcene": "pet\u00f2nega", "Ardesio": "pet\u00f2nega", "Aviatico": "pet\u00f2nega", "Azzano San Paolo": "pet\u00f2nega", "Bagnatica": "pet\u00f2nega", "Barbata": "pet\u00f2nega", "Bariano": "pet\u00f2nega", "Barzana": "pet\u00f2nega", "Berbenno": "pet\u00f2nega", "Bergamo": "pet\u00f2nega", "Berzo San Fermo": "pet\u00f2nega", "Bianzano": "pet\u00f2nega", "Blello": "pet\u00f2nega", "Bolgare": "pet\u00f2nega", "Bonate Sopra": "pet\u00f2nega", "Bonate Sotto": "pet\u00f2nega", "Borgo di Terzo": "pet\u00f2nega", "Bottanuco": "pet\u00f2nega", "Brembate": "pet\u00f2nega", "Brembate di Sopra": "pet\u00f2nega", "Brignano Gera d'Adda": "pet\u00f2nega", "Brumano": "pet\u00f2nega", "Brusaporto": "pet\u00f2nega", "Calcinate": "pet\u00f2nega", "Calcio": "pet\u00f2nega", "Calusco d'Adda": "pet\u00f2nega", "Calvenzano": "pet\u00f2nega", "Camerata Cornello": "pet\u00f2nega", "Canonica d'Adda": "pet\u00f2nega", "Capizzone": "pet\u00f2nega", "Capriate San Gervasio": "pet\u00f2nega", "Caprino Bergamasco": "pet\u00f2nega", "Caravaggio": "pet\u00f2nega", "Carobbio degli Angeli": "pet\u00f2nega", "Carona": "pet\u00f2nega", "Carvico": "pet\u00f2nega", "Casazza": "pet\u00f2nega", "Casnigo": "pet\u00f2nega", "Cassiglio": "pet\u00f2nega", "Castel Rozzone": "pet\u00f2nega", "Castelli Calepio": "pet\u00f2nega", "Castione della Presolana": "pet\u00f2nega", "Castro": "pet\u00f2nega", "Cavernago": "pet\u00f2nega", "Cazzano Sant'Andrea": "pet\u00f2nega", "Cenate Sopra": "pet\u00f2nega", "Cenate Sotto": "pet\u00f2nega", "Cene": "pet\u00f2nega", "Cerete": "pet\u00f2nega", "Chignolo d'Isola": "pet\u00f2nega", "Chiuduno": "pet\u00f2nega", "Cisano Bergamasco": "pet\u00f2nega", "Ciserano": "pet\u00f2nega", "Cividate al Piano": "pet\u00f2nega", "Clusone": "pet\u00f2nega", "Colere": "pet\u00f2nega", "Cologno al Serio": "pet\u00f2nega", "Colzate": "pet\u00f2nega", "Comun Nuovo": "pet\u00f2nega", "Corna Imagna": "pet\u00f2nega", "Cortenuova": "pet\u00f2nega", "Costa Serina": "pet\u00f2nega", "Costa Valle Imagna": "pet\u00f2nega", "Costa Volpino": "pet\u00f2nega", "Costa di Mezzate": "pet\u00f2nega", "Covo": "pet\u00f2nega", "Credaro": "pet\u00f2nega", "Curno": "pet\u00f2nega", "Cusio": "pet\u00f2nega", "Dalmine": "pet\u00f2nega", "Endine Gaiano": "pet\u00f2nega", "Entratico": "pet\u00f2nega", "Fara Gera d'Adda": "pet\u00f2nega", "Fara Olivana con Sola": "pet\u00f2nega", "Filago": "pet\u00f2nega", "Fino del Monte": "pet\u00f2nega", "Fiorano al Serio": "pet\u00f2nega", "Fontanella": "pet\u00f2nega", "Foresto Sparso": "pet\u00f2nega", "Fornovo San Giovanni": "pet\u00f2nega", "Fuipiano Valle Imagna": "pet\u00f2nega", "Gandellino": "pet\u00f2nega", "Gandino": "pet\u00f2nega", "Gazzaniga": "pet\u00f2nega", "Ghisalba": "pet\u00f2nega", "Gorlago": "pet\u00f2nega", "Gorle": "pet\u00f2nega", "Gorno": "pet\u00f2nega", "Grassobbio": "pet\u00f2nega", "Gromo": "pet\u00f2nega", "Grumello del Monte": "pet\u00f2nega", "Isso": "pet\u00f2nega", "Lallio": "pet\u00f2nega", "Leffe": "pet\u00f2nega", "Levate": "pet\u00f2nega", "Locatello": "pet\u00f2nega", "Lovere": "pet\u00f2nega", "Lurano": "pet\u00f2nega", "Madone": "pet\u00f2nega", "Mapello": "pet\u00f2nega", "Martinengo": "pet\u00f2nega", "Medolago": "pet\u00f2nega", "Misano di Gera d'Adda": "pet\u00f2nega", "Monasterolo del Castello": "pet\u00f2nega", "Montello": "pet\u00f2nega", "Morengo": "pet\u00f2nega", "Mornico al Serio": "pet\u00f2nega", "Mozzanica": "pet\u00f2nega", "Mozzo": "pet\u00f2nega", "Nembro": "pet\u00f2nega", "Oltre il Colle": "pet\u00f2nega", "Oltressenda Alta": "pet\u00f2nega", "Oneta": "pet\u00f2nega", "Onore": "pet\u00f2nega", "Orio al Serio": "pet\u00f2nega", "Osio Sopra": "pet\u00f2nega", "Osio Sotto": "pet\u00f2nega", "Pagazzano": "pet\u00f2nega", "Paladina": "pet\u00f2nega", "Palazzago": "pet\u00f2nega", "Palosco": "pet\u00f2nega", "Parre": "pet\u00f2nega", "Parzanica": "pet\u00f2nega", "Pedrengo": "pet\u00f2nega", "Peia": "pet\u00f2nega", "Pianico": "pet\u00f2nega", "Piario": "pet\u00f2nega", "Piazza Brembana": "pet\u00f2nega", "Pognano": "pet\u00f2nega", "Ponte Nossa": "pet\u00f2nega", "Ponte San Pietro": "pet\u00f2nega", "Ponteranica": "pet\u00f2nega", "Pontida": "pet\u00f2nega", "Pontirolo Nuovo": "pet\u00f2nega", "Pradalunga": "pet\u00f2nega", "Predore": "pet\u00f2nega", "Premolo": "pet\u00f2nega", "Presezzo": "pet\u00f2nega", "Ranica": "pet\u00f2nega", "Ranzanico": "pet\u00f2nega", "Riva di Solto": "pet\u00f2nega", "Rogno": "pet\u00f2nega", "Romano di Lombardia": "pet\u00f2nega", "Roncobello": "pet\u00f2nega", "Rota d'Imagna": "pet\u00f2nega", "Rovetta": "pet\u00f2nega", "San Giovanni Bianco": "pet\u00f2nega", "San Paolo d'Argon": "pet\u00f2nega", "San Pellegrino Terme": "pet\u00f2nega", "Sant'Omobono Terme": "pet\u00f2nega", "Santa Brigida": "pet\u00f2nega", "Sarnico": "pet\u00f2nega", "Scanzorosciate": "pet\u00f2nega", "Schilpario": "pet\u00f2nega", "Sedrina": "pet\u00f2nega", "Selvino": "pet\u00f2nega", "Seriate": "pet\u00f2nega", "Serina": "pet\u00f2nega", "Solza": "pet\u00f2nega", "Sorisole": "pet\u00f2nega", "Sotto il Monte Giovanni XXIII": "pet\u00f2nega", "Sovere": "pet\u00f2nega", "Spinone al Lago": "pet\u00f2nega", "Spirano": "pet\u00f2nega", "Stezzano": "pet\u00f2nega", "Suisio": "pet\u00f2nega", "Taleggio": "pet\u00f2nega", "Tavernola Bergamasca": "pet\u00f2nega", "Telgate": "pet\u00f2nega", "Terno d'Isola": "pet\u00f2nega", "Torre Boldone": "pet\u00f2nega", "Torre Pallavicina": "pet\u00f2nega", "Torre de' Busi": "pet\u00f2nega", "Torre de' Roveri": "pet\u00f2nega", "Trescore Balneario": "pet\u00f2nega", "Treviglio": "pet\u00f2nega", "Treviolo": "pet\u00f2nega", "Ubiale Clanezzo": "pet\u00f2nega", "Urgnano": "pet\u00f2nega", "Val Brembilla": "pet\u00f2nega", "Valbondione": "pet\u00f2nega", "Valbrembo": "pet\u00f2nega", "Valtorta": "pet\u00f2nega", "Vedeseta": "pet\u00f2nega", "Verdellino": "pet\u00f2nega", "Verdello": "pet\u00f2nega", "Vertova": "pet\u00f2nega", "Viadanica": "pet\u00f2nega", "Villa d'Alme": "pet\u00f2nega", "Villa d'Ogna": "pet\u00f2nega", "Villa di Serio": "pet\u00f2nega", "Villongo": "pet\u00f2nega", "Vilminore di Scalve": "pet\u00f2nega", "Zandobbio": "pet\u00f2nega", "Zanica": "pet\u00f2nega", "Zogno": "pet\u00f2nega", "Arzago d'Adda": "zab\u00e8ta", "Boltiere": "zab\u00e8ta", "Casirate d'Adda": "zab\u00e8ta", "Gaverina Terme": "zab\u00e8ta", "Roncola": "zab\u00e8ta", "Villa d'Adda": "zab\u00e8ta", "Averara": "Nessun Dato", "Azzone": "Nessun Dato", "Bossico": "Nessun Dato", "Branzi": "Nessun Dato", "Cornalba": "Nessun Dato", "Dossena": "Nessun Dato", "Fonteno": "Nessun Dato", "Foppolo": "Nessun Dato", "Gandosso": "Nessun Dato", "Grone": "Nessun Dato", "Isola di Fondra": "Nessun Dato", "Lenna": "Nessun Dato", "Luzzana": "Nessun Dato", "Mezzoldo": "Nessun Dato", "Moio de' Calvi": "Nessun Dato", "Olmo al Brembo": "Nessun Dato", "Ornica": "Nessun Dato", "Piazzatorre": "Nessun Dato", "Piazzolo": "Nessun Dato", "Pumenengo": "Nessun Dato", "Solto Collina": "Nessun Dato", "Songavazzo": "Nessun Dato", "Valgoglio": "Nessun Dato", "Valleve": "Nessun Dato", "Valnegra": "Nessun Dato", "Vigano San Martino": "Nessun Dato", "Bedulita": "Meda", "Bracca": "tofa", "Strozza": "tofa", "Vigolo": "tofa"}, "colors": {"pet\u00f2nega": "#ef4444", "zab\u00e8ta": "#f97316", "Nessun Dato": "#e5e7eb", "Meda": "#eab308", "tofa": "#84cc16"}}